setup.py
keylib/__init__.py
keylib/address_formatting.py
keylib/b58check.py
keylib/exceptions.py
keylib/hashing.py
keylib/key_formatting.py
keylib/private_key.py
keylib/public_key.py
keylib/public_key_encoding.py
keylib/utils.py
keylib.egg-info/PKG-INFO
keylib.egg-info/SOURCES.txt
keylib.egg-info/dependency_links.txt
keylib.egg-info/not-zip-safe
keylib.egg-info/requires.txt
keylib.egg-info/top_level.txt